MANIFEST.in
README.md
requirements.txt
setup.cfg
setup.py
versioneer.py
botcity/plugins/twilio/whatsapp/__init__.py
botcity/plugins/twilio/whatsapp/_version.py
botcity/plugins/twilio/whatsapp/plugin.py
botcity/plugins/twilio/whatsapp/utils.py
botcity_twilio_whatsapp_plugin.egg-info/PKG-INFO
botcity_twilio_whatsapp_plugin.egg-info/SOURCES.txt
botcity_twilio_whatsapp_plugin.egg-info/dependency_links.txt
botcity_twilio_whatsapp_plugin.egg-info/requires.txt
botcity_twilio_whatsapp_plugin.egg-info/top_level.txt