Metadata-Version: 2.1
Name: botcity-twilio-whatsapp-plugin
Version: 0.1.3
Home-page: https://bitbucket.org/botcitydev/bot-twilio-whatsapp-plugin-python.git
Requires-Python: >=3.7
